web_utils/__init__.py
web_utils/security.py
web_utils/tests.py
web_utils/forms.py
web_utils/extra.py
web_utils/json_form.py
web_utils/_pyramid/__init__.py
web_utils/code_loader/__init__.py
web_utils/code_loader/tests.py
web_utils/_django/__init__.py
web_utils/_sqlalchemy/__init__.py
web_utils-0.0.5.dist-info/METADATA
web_utils-0.0.5.dist-info/top_level.txt
web_utils-0.0.5.dist-info/DESCRIPTION.rst
web_utils-0.0.5.dist-info/RECORD
web_utils-0.0.5.dist-info/WHEEL
web_utils-0.0.5.dist-info/metadata.json
