Metadata-Version: 2.0
Name: web-utils
Version: 0.0.5
Summary: web_utils collection that used in web development process.
Home-page: http://github.com/winkidney/web_utils
Author: winkidney
Author-email: winkidney@gmail.com
License: GPLv3
Keywords: web development utils
Platform: UNKNOWN
Classifier: Programming Language :: Python
Classifier: Topic :: Utilities
Classifier: Topic :: Internet :: WWW/HTTP
Classifier: Topic :: Software Development :: Libraries
Provides-Extra: forms
Requires-Dist: wtforms; extra == 'forms'
Requires-Dist: jsonschema; extra == 'forms'
Provides-Extra: security
Requires-Dist: bcrypt; extra == 'security'
Provides-Extra: sqlalchemy
Requires-Dist: sqlalchemy; extra == 'sqlalchemy'
Requires-Dist: psycopg2; extra == 'sqlalchemy'
Requires-Dist: pycrypto; extra == 'sqlalchemy'
